MANIFEST.in
README.rst
setup.py
bookmarks/__init__.py
bookmarks/admin.py
bookmarks/forms.py
bookmarks/models.py
bookmarks/urls.py
bookmarks/views.py
bookmarks/site/__init__.py
bookmarks/site/settings.py
bookmarks/site/urls.py
bookmarks/site/templates/base.html
bookmarks/templates/bookmarks/add.html
bookmarks/templates/bookmarks/bookmark.html
bookmarks/templates/bookmarks/bookmarks.html
bookmarks/utils/__init__.py
bookmarks/utils/runner.py
mezzanine_bookmarks.egg-info/PKG-INFO
mezzanine_bookmarks.egg-info/SOURCES.txt
mezzanine_bookmarks.egg-info/dependency_links.txt
mezzanine_bookmarks.egg-info/entry_points.txt
mezzanine_bookmarks.egg-info/not-zip-safe
mezzanine_bookmarks.egg-info/requires.txt
mezzanine_bookmarks.egg-info/top_level.txt