Metadata-Version: 1.0
Name: mezzanine-bookmarks
Version: 0.1
Summary: Bookmark Service built on Django and Mezzanine.
Home-page: http://github.com/adieu/mezzanine-bookmarks
Author: Ivan Diao
Author-email: adieu@adieu.me
License: BSD
Platform: UNKNOWN
Classifier: Framework :: Django
Classifier: Intended Audience :: Developers
Classifier: Operating System :: OS Independent
Classifier: Topic :: Software Development
